{
  "cut": {
    "id": "cut",
    "desc_tagids": [],
    "description": null,
    "targ": 4,
    "eff": [{ "eff": -7.0, "targ": 0, "pow": 2.0 }],
    "use": 2.0,
    "desc_tags": [],
    "type": 1.0,
    "bt_tags": [1, 19, 9],
    "pow": 80.0,
    "name": "Cut Shot"
  },
  "allycover": {
    "id": "allycover",
    "desc_tagids": [],
    "description": null,
    "targ": 2,
    "eff": [{ "eff": 7.0, "targ": 1.0, "pow": 0.0 }],
    "use": 0.0,
    "desc_tags": [],
    "type": 3.0,
    "bt_tags": [22, 9],
    "pow": 0.0,
    "name": "Pipe"
  },
  "dare": {
    "id": "dare",
    "desc_tagids": [],
    "description": null,
    "targ": 0,
    "eff": [
      { "eff": 0.0, "targ": 3.0, "pow": 1.0 },
      { "eff": 1.0, "targ": 3.0, "pow": 1.0 }
    ],
    "use": 0.0,
    "desc_tags": [],
    "type": 1.0,
    "bt_tags": [1, 8, 30],
    "pow": 100.0,
    "name": "Challenge"
  },
  "heartup": {
    "id": "heartup",
    "desc_tagids": [],
    "description": null,
    "targ": 1,
    "eff": [{ "eff": 26, "targ": 2, "pow": 1.0 }],
    "use": 0.0,
    "desc_tags": [],
    "type": 5.0,
    "bt_tags": [31, 6],
    "pow": 0.0,
    "name": "Battle Cry"
  },
  "dig": {
    "id": "dig",
    "desc_tagids": [],
    "description": null,
    "targ": 1,
    "eff": [{ "eff": 26, "targ": 0.0, "pow": 1.0 }],
    "use": 0.0,
    "desc_tags": [],
    "type": 3.0,
    "bt_tags": [22, 31],
    "pow": 0.0,
    "name": "Dig"
  },
  "refresh": {
    "id": "refresh",
    "desc_tagids": [],
    "description": null,
    "targ": 2,
    "eff": [{ "eff": 8, "targ": 1.0, "pow": 0.14999999999999999 }],
    "use": 0.0,
    "desc_tags": [],
    "type": 3.0,
    "bt_tags": [22, 9, 16],
    "pow": 0.0,
    "name": "Refresh"
  },
  "sideshot": {
    "id": "sideshot",
    "desc_tagids": [],
    "description": null,
    "targ": 12,
    "eff": [{ "eff": 7.0, "targ": 3.0, "pow": 2.0 }],
    "use": 0.0,
    "desc_tags": [],
    "type": 0.0,
    "bt_tags": [0, 9],
    "pow": 35.0,
    "name": "Sidewinder"
  },
  "crowd": {
    "id": "crowd",
    "desc_tagids": [],
    "description": null,
    "targ": 0,
    "eff": [{ "eff": 43, "targ": 7, "pow": 3.0 }],
    "use": 0.0,
    "desc_tags": [],
    "type": 4.0,
    "bt_tags": [23, 12],
    "pow": 0.0,
    "name": "Rally"
  },
  "curse": {
    "id": "curse",
    "desc_tagids": [],
    "description": null,
    "targ": 1,
    "eff": [
      { "eff": 0.0, "targ": 0.0, "pow": 1.0 },
      { "eff": 3.0, "targ": 0.0, "pow": 1.0 }
    ],
    "use": 0.0,
    "desc_tags": [],
    "type": 4.0,
    "bt_tags": [23, 27, 28, 7],
    "pow": 0.0,
    "name": "Flex"
  },
  "overthink": {
    "id": "overthink",
    "desc_tagids": [],
    "description": null,
    "targ": 1,
    "eff": [
      { "eff": 2.0, "targ": 0.0, "pow": 3.0 },
      { "eff": 39, "targ": 0.0, "pow": 1.0 }
    ],
    "use": 0.0,
    "desc_tags": [],
    "type": 4.0,
    "bt_tags": [23, 27, 30],
    "pow": 0.0,
    "name": "Overthink"
  },
  "thunder": {
    "id": "thunder",
    "desc_tagids": [],
    "description": null,
    "targ": 8,
    "eff": [],
    "use": 2.0,
    "desc_tags": [],
    "type": 0.0,
    "bt_tags": [0, 8, 19, 9],
    "pow": 110.0,
    "name": "Thunder"
  },
  "rush": {
    "id": "rush",
    "desc_tagids": [],
    "description": null,
    "targ": 2,
    "eff": [{ "eff": 7.0, "targ": 0.0, "pow": 1.0 }],
    "use": 0.0,
    "desc_tags": [],
    "type": 3.0,
    "bt_tags": [22, 9],
    "pow": 0.0,
    "name": "Net Rush"
  },
  "whirlwind": {
    "id": "whirlwind",
    "desc_tagids": [],
    "description": null,
    "targ": 4,
    "eff": [{ "eff": 30, "targ": 3.0, "pow": 1.0 }],
    "use": 0.0,
    "desc_tags": [],
    "type": 5.0,
    "bt_tags": [9, 11],
    "pow": 0.0,
    "name": "Cyclone"
  },
  "construct": {
    "id": "construct",
    "desc_tagids": [],
    "description": null,
    "targ": 0,
    "eff": [
      { "eff": 56, "targ": 0.0, "pow": 0.0 },
      { "eff": 8.0, "targ": 0.0, "pow": -0.34000000000000002 },
      { "eff": 57, "targ": 0.0, "pow": 0.0 }
    ],
    "use": 1.0,
    "desc_tags": [],
    "type": 4.0,
    "bt_tags": [23, 20, 25, 30],
    "pow": 0.0,
    "name": "Build"
  },
  "hazeball": {
    "id": "hazeball",
    "desc_tagids": [],
    "description": null,
    "targ": 0,
    "eff": [{ "eff": 34, "targ": 3, "pow": 1.0 }],
    "use": 0.0,
    "desc_tags": [],
    "type": 2.0,
    "bt_tags": [2],
    "pow": 65.0,
    "name": "Numbshot"
  },
  "spitball": {
    "id": "spitball",
    "desc_tagids": [],
    "description": null,
    "targ": 0,
    "eff": [{ "eff": 12, "targ": 3.0, "pow": 1.0 }],
    "use": 0.0,
    "desc_tags": [],
    "type": 2.0,
    "bt_tags": [2, 14, 37],
    "pow": 75.0,
    "name": "Spitball"
  },
  "targethp": {
    "id": "targethp",
    "desc_tagids": [],
    "description": null,
    "targ": 0,
    "eff": [{ "eff": 33.0, "targ": 0.0, "pow": 8.0 }],
    "use": 0.0,
    "desc_tags": [],
    "type": 2.0,
    "bt_tags": [2, 8],
    "pow": 120.0,
    "name": "Soulcrusher"
  },
  "charm": {
    "id": "charm",
    "desc_tagids": [],
    "description": null,
    "targ": 4,
    "eff": [{ "eff": 0.0, "targ": 3.0, "pow": -2.0 }],
    "use": 0.0,
    "desc_tags": [],
    "type": 4.0,
    "bt_tags": [23, 9, 36],
    "pow": 0.0,
    "name": "Goo-Goo Eyes"
  },
  "allnervous": {
    "id": "allnervous",
    "desc_tagids": [],
    "description": null,
    "targ": 1,
    "eff": [{ "eff": 6.0, "targ": 7.0, "pow": 1.0 }],
    "use": 2.0,
    "desc_tags": [],
    "type": 5.0,
    "bt_tags": [19, 30, 29, 37],
    "pow": 0.0,
    "name": "Upsetting Comment"
  },
  "lifepass": {
    "id": "lifepass",
    "desc_tagids": [],
    "description": null,
    "targ": 8,
    "eff": [
      { "eff": 8.0, "targ": 0.0, "pow": -1.0 },
      { "eff": 47, "targ": 3.0, "pow": 1.0 },
      { "eff": 30.0, "targ": 3.0, "pow": 1.0 }
    ],
    "use": 0.0,
    "desc_tags": [],
    "type": 5.0,
    "bt_tags": [9, 30, 39, 18],
    "pow": 0.0,
    "name": "Torch Pass"
  },
  "sweatup": {
    "id": "sweatup",
    "desc_tagids": [],
    "description": null,
    "targ": 4,
    "eff": [{ "eff": 23, "targ": 3.0, "pow": 1.0 }],
    "use": 0.0,
    "desc_tags": [],
    "type": 5.0,
    "bt_tags": [9, 35, 37],
    "pow": 0.0,
    "name": "Heat Up"
  },
  "moon": {
    "id": "moon",
    "desc_tagids": [],
    "description": null,
    "targ": 8,
    "eff": [],
    "use": 1.0,
    "desc_tags": [],
    "type": 2.0,
    "bt_tags": [2, 8, 20, 9],
    "pow": 100.0,
    "name": "Rainbow"
  },
  "netattack": {
    "id": "netattack",
    "desc_tagids": [],
    "description": null,
    "targ": 0,
    "eff": [{ "eff": 7.0, "targ": 0.0, "pow": 1.0 }],
    "use": 0.0,
    "desc_tags": [],
    "type": 2.0,
    "bt_tags": [2],
    "pow": 70.0,
    "name": "Sneak Attack"
  },
  "threat": {
    "id": "threat",
    "desc_tagids": [],
    "description": null,
    "targ": 4,
    "eff": [{ "eff": 38.0, "targ": 3.0, "pow": 1.0 }],
    "use": 0.0,
    "desc_tags": [],
    "type": 5.0,
    "bt_tags": [9, 37],
    "pow": 0.0,
    "name": "Intimidate"
  },
  "heart": {
    "id": "heart",
    "desc_tagids": [],
    "description": null,
    "targ": 0,
    "eff": [],
    "use": 0.0,
    "desc_tags": [],
    "type": 1.0,
    "bt_tags": [1],
    "pow": 85.0,
    "name": "Bring the Heat"
  },
  "noisytag": {
    "id": "noisytag",
    "desc_tagids": [],
    "description": null,
    "targ": 8,
    "eff": [
      { "eff": 30, "targ": 3.0, "pow": 1.0 },
      { "eff": 53, "targ": 3.0, "pow": 0.0 },
      { "eff": 14, "targ": 3.0, "pow": 1.0 },
      { "eff": 12, "targ": 3.0, "pow": 2.0 }
    ],
    "use": 0.0,
    "desc_tags": [],
    "type": 5.0,
    "bt_tags": [9, 18, 33, 30],
    "pow": 0.0,
    "name": "Dramatic Exit"
  },
  "allyprotect": {
    "id": "allyprotect",
    "desc_tagids": [],
    "description": null,
    "targ": 1,
    "eff": [
      { "eff": 14, "targ": 0.0, "pow": 1.0 },
      { "eff": 12, "targ": 0, "pow": 2.0 }
    ],
    "use": 0.0,
    "desc_tags": [],
    "type": 5.0,
    "bt_tags": [33],
    "pow": 0.0,
    "name": "Mighty Yell"
  },
  "set": {
    "id": "set",
    "desc_tagids": [],
    "description": null,
    "targ": 2,
    "eff": [{ "eff": 26, "targ": 1.0, "pow": 1.0 }],
    "use": 0.0,
    "desc_tags": [],
    "type": 3.0,
    "bt_tags": [22, 9, 31, 6],
    "pow": 0.0,
    "name": "Set"
  },
  "storedpower": {
    "id": "storedpower",
    "desc_tagids": [],
    "description": null,
    "targ": 0,
    "eff": [{ "eff": 33.0, "targ": 0.0, "pow": 10.0 }],
    "use": 0.0,
    "desc_tags": [],
    "type": 0.0,
    "bt_tags": [0],
    "pow": 15.0,
    "name": "Energized"
  },
  "pepshot": {
    "id": "pepshot",
    "desc_tagids": [],
    "description": null,
    "targ": 0,
    "eff": [{ "eff": 1.0, "targ": 0.0, "pow": 1.0 }],
    "use": 0.0,
    "desc_tags": [],
    "type": 1.0,
    "bt_tags": [1, 27],
    "pow": 40.0,
    "name": "Pepshot"
  },
  "stresspass": {
    "id": "stresspass",
    "desc_tagids": [],
    "description": null,
    "targ": 2,
    "eff": [
      { "eff": 15.0, "targ": 1.0, "pow": 2.0 },
      { "eff": 39, "targ": 2, "pow": 1.0 }
    ],
    "use": 0.0,
    "desc_tags": [],
    "type": 3.0,
    "bt_tags": [22, 9, 6, 30],
    "pow": 0.0,
    "name": "Demanding Set"
  },
  "superpower": {
    "id": "superpower",
    "desc_tagids": [],
    "description": null,
    "targ": 0,
    "eff": [
      { "eff": 0.0, "targ": 0.0, "pow": -1.0 },
      { "eff": 3.0, "targ": 0.0, "pow": -1.0 }
    ],
    "use": 0.0,
    "desc_tags": [],
    "type": 0.0,
    "bt_tags": [0, 8],
    "pow": 110.0,
    "name": "Overpower"
  },
  "tool": {
    "id": "tool",
    "desc_tagids": [],
    "description": null,
    "targ": 13,
    "eff": [],
    "use": 0.0,
    "desc_tags": [],
    "type": 2.0,
    "bt_tags": [2, 9],
    "pow": 95.0,
    "name": "Tool"
  },
  "rest": {
    "id": "rest",
    "desc_tagids": [],
    "description": null,
    "targ": 1,
    "eff": [
      { "eff": 47, "targ": 0.0, "pow": 1.0 },
      { "eff": 29.0, "targ": 0.0, "pow": 4.0 }
    ],
    "use": 0.0,
    "desc_tags": [],
    "type": 4.0,
    "bt_tags": [23, 39, 30],
    "pow": 0.0,
    "name": "Doze"
  },
  "sidespin": {
    "id": "sidespin",
    "desc_tagids": [],
    "description": null,
    "targ": 12,
    "eff": [],
    "use": 0.0,
    "desc_tags": [],
    "type": 2.0,
    "bt_tags": [2, 9],
    "pow": 60.0,
    "name": "Slice"
  },
  "overheat": {
    "id": "overheat",
    "desc_tagids": [],
    "description": null,
    "targ": 0,
    "eff": [{ "eff": 1.0, "targ": 0.0, "pow": -2.0 }],
    "use": 0.0,
    "desc_tags": [],
    "type": 1.0,
    "bt_tags": [1, 8],
    "pow": 110.0,
    "name": "Burnout"
  },
  "dropshot": {
    "id": "dropshot",
    "desc_tagids": [],
    "description": null,
    "targ": 0,
    "eff": [{ "eff": 7.0, "targ": 3.0, "pow": 1.0 }],
    "use": 0.0,
    "desc_tags": [],
    "type": 2.0,
    "bt_tags": [2],
    "pow": 55.0,
    "name": "Lure Shot"
  },
  "breakswipe": {
    "id": "breakswipe",
    "desc_tagids": [],
    "description": null,
    "targ": 0,
    "eff": [{ "eff": 0.0, "targ": 3.0, "pow": -1.0 }],
    "use": 0.0,
    "desc_tags": [],
    "type": 0.0,
    "bt_tags": [0, 36],
    "pow": 60.0,
    "name": "Kneebender"
  },
  "poisonhit": {
    "id": "poisonhit",
    "desc_tagids": [],
    "description": null,
    "targ": 8,
    "eff": [{ "eff": 23, "targ": 3, "pow": 1.0 }],
    "use": 0.0,
    "desc_tags": [],
    "type": 2.0,
    "bt_tags": [2, 9, 35, 37],
    "pow": 25.0,
    "name": "Cornershot"
  },
  "enemyboosts": {
    "id": "enemyboosts",
    "desc_tagids": [],
    "description": null,
    "targ": 0,
    "eff": [{ "eff": 33.0, "targ": 0.0, "pow": 11.0 }],
    "use": 0.0,
    "desc_tags": [],
    "type": 1.0,
    "bt_tags": [1],
    "pow": 50.0,
    "name": "Toppler"
  },
  "meditate": {
    "id": "meditate",
    "desc_tagids": [],
    "description": null,
    "targ": 1,
    "eff": [
      { "eff": 2.0, "targ": 0.0, "pow": 1.0 },
      { "eff": 5.0, "targ": 0.0, "pow": 1.0 },
      { "eff": 4.0, "targ": 0.0, "pow": 1.0 }
    ],
    "use": 0.0,
    "desc_tags": [],
    "type": 4.0,
    "bt_tags": [23, 27, 28, 7],
    "pow": 0.0,
    "name": "Meditate"
  },
  "cover": {
    "id": "cover",
    "desc_tagids": [],
    "description": null,
    "targ": 2,
    "eff": [{ "eff": 7.0, "targ": 0.0, "pow": 0.0 }],
    "use": 0.0,
    "desc_tags": [],
    "type": 3.0,
    "bt_tags": [22, 9],
    "pow": 0.0,
    "name": "Cover"
  },
  "freeball": {
    "id": "freeball",
    "desc_tagids": [],
    "description": null,
    "targ": 2,
    "eff": [
      { "eff": 10.0, "targ": 1.0, "pow": 1.0 },
      { "eff": 8.0, "targ": 0.0, "pow": -0.34000000000000002 }
    ],
    "use": 0.0,
    "desc_tags": [],
    "type": 3.0,
    "bt_tags": [22, 9, 26, 30],
    "pow": 0.0,
    "name": "Updraft"
  },
  "taunt": {
    "id": "taunt",
    "desc_tagids": [],
    "description": null,
    "targ": 4,
    "eff": [{ "eff": 12.0, "targ": 3.0, "pow": 2.0 }],
    "use": 0.0,
    "desc_tags": [],
    "type": 4.0,
    "bt_tags": [23, 9, 14, 37],
    "pow": 0.0,
    "name": "Provoke"
  },
  "???": {
    "id": "???",
    "desc_tagids": [],
    "description": null,
    "targ": 0.0,
    "eff": [],
    "use": 0.0,
    "desc_tags": [],
    "type": 6.0,
    "bt_tags": [],
    "pow": 0.0,
    "name": "Unrevealed"
  },
  "snipe": {
    "id": "snipe",
    "desc_tagids": [],
    "description": null,
    "targ": 0,
    "eff": [{ "eff": 33, "targ": 0.0, "pow": 22 }],
    "use": 0.0,
    "desc_tags": [],
    "type": 2.0,
    "bt_tags": [2],
    "pow": 60.0,
    "name": "Snipe"
  },
  "jazzpass": {
    "id": "jazzpass",
    "desc_tagids": [],
    "description": null,
    "targ": 2,
    "eff": [
      { "eff": 7.0, "targ": 1.0, "pow": 1.0 },
      { "eff": 26, "targ": 1.0, "pow": 1.0 }
    ],
    "use": 2.0,
    "desc_tags": [],
    "type": 3.0,
    "bt_tags": [22, 19, 9, 21, 31, 6],
    "pow": 0.0,
    "name": "Perfect Pass"
  },
  "substitute": {
    "id": "substitute",
    "desc_tagids": [],
    "description": null,
    "targ": 1,
    "eff": [
      { "eff": 8.0, "targ": 0.0, "pow": -0.33000000000000002 },
      { "eff": 19.0, "targ": 0.0, "pow": 2.0 }
    ],
    "use": 0.0,
    "desc_tags": [],
    "type": 4.0,
    "bt_tags": [23, 30, 32],
    "pow": 0.0,
    "name": "Tough Front"
  },
  "tagout": {
    "id": "tagout",
    "desc_tagids": [],
    "description": null,
    "targ": 0,
    "eff": [],
    "use": 0.0,
    "desc_tags": [],
    "type": 9.0,
    "bt_tags": [],
    "pow": 0.0,
    "name": "Tag Out"
  },
  "lowattks": {
    "id": "lowattks",
    "desc_tagids": [],
    "description": null,
    "targ": 4,
    "eff": [
      { "eff": 0.0, "targ": 3.0, "pow": -1.0 },
      { "eff": 2.0, "targ": 3.0, "pow": -1.0 }
    ],
    "use": 0.0,
    "desc_tags": [],
    "type": 4.0,
    "bt_tags": [23, 9, 36],
    "pow": 0.0,
    "name": "Jeer"
  },
  "sensihit": {
    "id": "sensihit",
    "desc_tagids": [],
    "description": null,
    "targ": 0,
    "eff": [{ "eff": 38.0, "targ": 3.0, "pow": 2.0 }],
    "use": 0.0,
    "desc_tags": [],
    "type": 0.0,
    "bt_tags": [0, 37],
    "pow": 40.0,
    "name": "Zinger"
  },
  "shakenmind": {
    "id": "shakenmind",
    "desc_tagids": [],
    "description": null,
    "targ": 0,
    "eff": [{ "eff": 13.0, "targ": 3.0, "pow": 1.0 }],
    "use": 0.0,
    "desc_tags": [],
    "type": 2.0,
    "bt_tags": [2, 37],
    "pow": 40.0,
    "name": "Twisted"
  },
  "desperate": {
    "id": "desperate",
    "desc_tagids": [],
    "description": null,
    "targ": 0,
    "eff": [
      { "eff": 17.0, "targ": 0.0, "pow": 0.0 },
      { "eff": 39.0, "targ": 0.0, "pow": 1.0 }
    ],
    "use": 0.0,
    "desc_tags": [],
    "type": 1.0,
    "bt_tags": [1, 30],
    "pow": 75.0,
    "name": "Desperate Dive"
  },
  "minddown": {
    "id": "minddown",
    "desc_tagids": [],
    "description": null,
    "targ": 0,
    "eff": [{ "eff": 2.0, "targ": 3.0, "pow": -1.0 }],
    "use": 0.0,
    "desc_tags": [],
    "type": 1.0,
    "bt_tags": [1, 36],
    "pow": 70.0,
    "name": "Jammer"
  },
  "contest": {
    "id": "contest",
    "desc_tagids": [],
    "description": null,
    "targ": 0,
    "eff": [{ "eff": 33, "targ": 0.0, "pow": 23 }],
    "use": 0.0,
    "desc_tags": [],
    "type": 1.0,
    "bt_tags": [1, 8],
    "pow": 110.0,
    "name": "Contest"
  },
  "protectcheer": {
    "id": "protectcheer",
    "desc_tagids": [],
    "description": null,
    "targ": 1,
    "eff": [
      { "eff": 53, "targ": 0.0, "pow": 0.0 },
      { "eff": 19, "targ": 0.0, "pow": 1.0 },
      { "eff": 12, "targ": 0.0, "pow": 2.0 },
      { "eff": 15, "targ": 1, "pow": 1.0 }
    ],
    "use": 0.0,
    "desc_tags": [],
    "type": 5.0,
    "bt_tags": [32, 6],
    "pow": 0.0,
    "name": "Inspiring Defense"
  },
  "sting": {
    "id": "sting",
    "desc_tagids": [],
    "description": null,
    "targ": 4,
    "eff": [
      { "eff": 29, "targ": 3.0, "pow": 2.0 },
      { "eff": 8, "targ": 0.0, "pow": -0.20000000000000001 }
    ],
    "use": 0.0,
    "desc_tags": [],
    "type": 5.0,
    "bt_tags": [9, 37],
    "pow": 0.0,
    "name": "Sting"
  },
  "body": {
    "id": "body",
    "desc_tagids": [],
    "description": null,
    "targ": 0,
    "eff": [],
    "use": 0.0,
    "desc_tags": [],
    "type": 0.0,
    "bt_tags": [0],
    "pow": 90.0,
    "name": "Thump"
  },
  "allyrush": {
    "id": "allyrush",
    "desc_tagids": [],
    "description": null,
    "targ": 2,
    "eff": [{ "eff": 7.0, "targ": 1.0, "pow": 1.0 }],
    "use": 0.0,
    "desc_tags": [],
    "type": 3.0,
    "bt_tags": [22, 9, 21],
    "pow": 0.0,
    "name": "Forward Pass"
  },
  "sweatall": {
    "id": "sweatall",
    "desc_tagids": [],
    "description": null,
    "targ": 1,
    "eff": [{ "eff": 23, "targ": 7, "pow": 1.0 }],
    "use": 0.0,
    "desc_tags": [],
    "type": 5.0,
    "bt_tags": [30, 35, 37],
    "pow": 0.0,
    "name": "Heat Wave"
  },
  "meter": {
    "id": "meter",
    "desc_tagids": [],
    "description": null,
    "targ": 4,
    "eff": [
      { "eff": 12.0, "targ": 3.0, "pow": 2.0 },
      { "eff": 60, "targ": 0.0, "pow": 1.0 }
    ],
    "use": 0.0,
    "desc_tags": [],
    "type": 4.0,
    "bt_tags": [23, 9, 14, 37],
    "pow": 0.0,
    "name": "Rowdy"
  },
  "commit": {
    "id": "commit",
    "desc_tagids": [],
    "description": null,
    "targ": 0,
    "eff": [{ "eff": 6.0, "targ": 0.0, "pow": 1.0 }],
    "use": 0.0,
    "desc_tags": [],
    "type": 1.0,
    "bt_tags": [1, 8, 30],
    "pow": 100.0,
    "name": "Supercommit"
  },
  "reversal": {
    "id": "reversal",
    "desc_tagids": [],
    "description": null,
    "targ": 0,
    "eff": [{ "eff": 33.0, "targ": 0.0, "pow": 1.0 }],
    "use": 0.0,
    "desc_tags": [],
    "type": 1.0,
    "bt_tags": [1, 8],
    "pow": 160.0,
    "name": "Turnabout"
  },
  "stress": {
    "id": "stress",
    "desc_tagids": [],
    "description": null,
    "targ": 4,
    "eff": [{ "eff": 39, "targ": 3.0, "pow": 1.0 }],
    "use": 0.0,
    "desc_tags": [],
    "type": 5.0,
    "bt_tags": [9, 37],
    "pow": 0.0,
    "name": "Frazzle"
  },
  "serve": {
    "id": "serve",
    "desc_tagids": [],
    "description": null,
    "targ": 0,
    "eff": [{ "eff": 33.0, "targ": 0.0, "pow": 7.0 }],
    "use": 0.0,
    "desc_tags": [],
    "type": 0.0,
    "bt_tags": [0],
    "pow": 70.0,
    "name": "Muscle Memory"
  },
  "mindpass": {
    "id": "mindpass",
    "desc_tagids": [],
    "description": null,
    "targ": 2,
    "eff": [{ "eff": 2.0, "targ": 1.0, "pow": 1.0 }],
    "use": 0.0,
    "desc_tags": [],
    "type": 3.0,
    "bt_tags": [22, 9, 5],
    "pow": 0.0,
    "name": "Tactical Pass"
  },
  "healhit2": {
    "id": "healhit2",
    "desc_tagids": [],
    "description": null,
    "targ": 0,
    "eff": [{ "eff": 8.0, "targ": 0.0, "pow": 0.10000000000000001 }],
    "use": 0.0,
    "desc_tags": [],
    "type": 0.0,
    "bt_tags": [0],
    "pow": 75.0,
    "name": "Power Sap"
  },
  "fieldclear": {
    "id": "fieldclear",
    "desc_tagids": [],
    "description": null,
    "targ": 0,
    "eff": [
      { "eff": 46, "targ": 7, "pow": 0.0 },
      { "eff": 8, "targ": 6, "pow": 0.080000000000000002 }
    ],
    "use": 0.0,
    "desc_tags": [],
    "type": 4.0,
    "bt_tags": [23, 15, 16],
    "pow": 0.0,
    "name": "Clear Field"
  },
  "superquick": {
    "id": "superquick",
    "desc_tagids": [],
    "description": null,
    "targ": 2,
    "eff": [{ "eff": 0.0, "targ": 1.0, "pow": 2.0 }],
    "use": 2.0,
    "desc_tags": [],
    "type": 3.0,
    "bt_tags": [22, 19, 9, 3],
    "pow": 0.0,
    "name": "Super Quick"
  },
  "distraction": {
    "id": "distraction",
    "desc_tagids": [],
    "description": null,
    "targ": 1,
    "eff": [{ "eff": 14.0, "targ": 0.0, "pow": 1.0 }],
    "use": 2.0,
    "desc_tags": [],
    "type": 5.0,
    "bt_tags": [19, 33],
    "pow": 0.0,
    "name": "Distraction"
  },
  "tagattack": {
    "id": "tagattack",
    "desc_tagids": [],
    "description": null,
    "targ": 0,
    "eff": [{ "eff": 33, "targ": 0.0, "pow": 20 }],
    "use": 0.0,
    "desc_tags": [],
    "type": 0.0,
    "bt_tags": [0],
    "pow": 60.0,
    "name": "Momentum"
  },
  "scoreboosted": {
    "id": "scoreboosted",
    "desc_tagids": [],
    "description": null,
    "targ": 0,
    "eff": [{ "eff": 33.0, "targ": 0.0, "pow": 15.0 }],
    "use": 0.0,
    "desc_tags": [],
    "type": 1.0,
    "bt_tags": [1],
    "pow": 60.0,
    "name": "Comeback"
  },
  "mindbomb": {
    "id": "mindbomb",
    "desc_tagids": [],
    "description": null,
    "targ": 0,
    "eff": [{ "eff": 36, "targ": 5, "pow": 1.0 }],
    "use": 0.0,
    "desc_tags": [],
    "type": 2.0,
    "bt_tags": [2, 38],
    "pow": 45.0,
    "name": "Mindfield"
  },
  "facade": {
    "id": "facade",
    "desc_tagids": [],
    "description": null,
    "targ": 0,
    "eff": [{ "eff": 33.0, "targ": 0.0, "pow": 12 }],
    "use": 0.0,
    "desc_tags": [],
    "type": 1.0,
    "bt_tags": [1],
    "pow": 65.0,
    "name": "Grit"
  },
  "steal": {
    "id": "steal",
    "desc_tagids": [],
    "description": null,
    "targ": 1,
    "eff": [
      { "eff": 20, "targ": 0.0, "pow": 1.0 },
      { "eff": 7.0, "targ": 0.0, "pow": 1.0 }
    ],
    "use": 0.0,
    "desc_tags": [],
    "type": 4.0,
    "bt_tags": [23],
    "pow": 0.0,
    "name": "Steal"
  },
  "topspin": {
    "id": "topspin",
    "desc_tagids": [],
    "description": null,
    "targ": 12,
    "eff": [],
    "use": 0.0,
    "desc_tags": [],
    "type": 0.0,
    "bt_tags": [0, 9],
    "pow": 50.0,
    "name": "Bounce"
  },
  "float": {
    "id": "float",
    "desc_tagids": [],
    "description": null,
    "targ": 0,
    "eff": [{ "eff": 7.0, "targ": 3.0, "pow": 0.0 }],
    "use": 0.0,
    "desc_tags": [],
    "type": 2.0,
    "bt_tags": [2],
    "pow": 65.0,
    "name": "Floater"
  },
  "startermind": {
    "id": "startermind",
    "desc_tagids": [],
    "description": null,
    "targ": 0,
    "eff": [],
    "use": 0.0,
    "desc_tags": [],
    "type": 2.0,
    "bt_tags": [2],
    "pow": 40.0,
    "name": "Practice Shot"
  },
  "steamattack": {
    "id": "steamattack",
    "desc_tagids": [],
    "description": null,
    "targ": 1,
    "eff": [{ "eff": 23, "targ": 3.0, "pow": 2.0 }],
    "use": 0.0,
    "desc_tags": [],
    "type": 1.0,
    "bt_tags": [1, 35, 37],
    "pow": 1.0,
    "name": "Steamer"
  },
  "nettle": {
    "id": "nettle",
    "desc_tagids": [],
    "description": null,
    "targ": 4,
    "eff": [{ "eff": 8.0, "targ": 3.0, "pow": -0.20000000000000001 }],
    "use": 0.0,
    "desc_tags": [],
    "type": 4.0,
    "bt_tags": [23, 9],
    "pow": 0.0,
    "name": "Nettle"
  },
  "jazzattack": {
    "id": "jazzattack",
    "desc_tagids": [],
    "description": null,
    "targ": 0,
    "eff": [{ "eff": -26, "targ": 0.0, "pow": 1.0 }],
    "use": 0.0,
    "desc_tags": [],
    "type": 1.0,
    "bt_tags": [1],
    "pow": 55.0,
    "name": "Thriller"
  },
  "teleport": {
    "id": "teleport",
    "desc_tagids": [],
    "description": null,
    "targ": 1,
    "eff": [{ "eff": 28.0, "targ": 1.0, "pow": 1.0 }],
    "use": 0.0,
    "desc_tags": [],
    "type": 4.0,
    "bt_tags": [23],
    "pow": 0.0,
    "name": "Teleport"
  },
  "snore": {
    "id": "snore",
    "desc_tagids": [],
    "description": null,
    "targ": 0,
    "eff": [{ "eff": 61, "targ": 0, "pow": 1.0 }],
    "use": 0.0,
    "desc_tags": [],
    "type": 1.0,
    "bt_tags": [1],
    "pow": 50.0,
    "name": "Relentless"
  },
  "swordsdance": {
    "id": "swordsdance",
    "desc_tagids": [],
    "description": null,
    "targ": 1,
    "eff": [{ "eff": 0.0, "targ": 0.0, "pow": 2.0 }],
    "use": 0.0,
    "desc_tags": [],
    "type": 5.0,
    "bt_tags": [27],
    "pow": 0.0,
    "name": "Pump Up"
  },
  "pursuit": {
    "id": "pursuit",
    "desc_tagids": [],
    "description": null,
    "targ": 0,
    "eff": [{ "eff": 33, "targ": 0.0, "pow": 5 }],
    "use": 0.0,
    "desc_tags": [],
    "type": 2.0,
    "bt_tags": [2],
    "pow": 55.0,
    "name": "Pressure"
  },
  "followme": {
    "id": "followme",
    "desc_tagids": [],
    "description": null,
    "targ": 1,
    "eff": [{ "eff": 14.0, "targ": 0.0, "pow": 1.0 }],
    "use": 0.0,
    "desc_tags": [],
    "type": 4.0,
    "bt_tags": [23, 33],
    "pow": 0.0,
    "name": "Whistle"
  },
  "mdefup": {
    "id": "mdefup",
    "desc_tagids": [],
    "description": null,
    "targ": 1,
    "eff": [{ "eff": 5.0, "targ": 0.0, "pow": 2.0 }],
    "use": 0.0,
    "desc_tags": [],
    "type": 5.0,
    "bt_tags": [28, 7],
    "pow": 0.0,
    "name": "Mind Read"
  },
  "callout": {
    "id": "callout",
    "desc_tagids": [],
    "description": null,
    "targ": 2,
    "eff": [{ "eff": 16.0, "targ": 1.0, "pow": 1.0 }],
    "use": 0.0,
    "desc_tags": [],
    "type": 4.0,
    "bt_tags": [23, 9, 28, 7],
    "pow": 0.0,
    "name": "Call Out"
  },
  "hyperbeam": {
    "id": "hyperbeam",
    "desc_tagids": [],
    "description": null,
    "targ": 0,
    "eff": [{ "eff": 29.0, "targ": 0.0, "pow": 2.0 }],
    "use": 2.0,
    "desc_tags": [],
    "type": 0.0,
    "bt_tags": [0, 8, 19, 30],
    "pow": 135.0,
    "name": "Hyperspike"
  },
  "dragontail": {
    "id": "dragontail",
    "desc_tagids": [],
    "description": null,
    "targ": 0,
    "eff": [{ "eff": 30, "targ": 3, "pow": 1.0 }],
    "use": 0.0,
    "desc_tags": [],
    "type": 1.0,
    "bt_tags": [1, 11],
    "pow": 60.0,
    "name": "Tornadoball"
  },
  "rocksmash": {
    "id": "rocksmash",
    "desc_tagids": [],
    "description": null,
    "targ": 0,
    "eff": [{ "eff": 3.0, "targ": 3.0, "pow": -1.0 }],
    "use": 0.0,
    "desc_tags": [],
    "type": 0.0,
    "bt_tags": [0, 36, 3],
    "pow": 50.0,
    "name": "Breaker"
  },
  "damagedattack": {
    "id": "damagedattack",
    "desc_tagids": [],
    "description": null,
    "targ": 0,
    "eff": [{ "eff": 33, "targ": 0.0, "pow": 18 }],
    "use": 0.0,
    "desc_tags": [],
    "type": 1.0,
    "bt_tags": [1],
    "pow": 75.0,
    "name": "Counter"
  },
  "heartdown": {
    "id": "heartdown",
    "desc_tagids": [],
    "description": null,
    "targ": 0,
    "eff": [{ "eff": 1.0, "targ": 3.0, "pow": -1.0 }],
    "use": 0.0,
    "desc_tags": [],
    "type": 2.0,
    "bt_tags": [2, 36],
    "pow": 75.0,
    "name": "Heartbreaker"
  },
  "move": {
    "id": "move",
    "desc_tagids": [],
    "description": null,
    "targ": 0,
    "eff": [{ "eff": 57, "targ": 0.0, "pow": 3.0 }],
    "use": 0.0,
    "desc_tags": [],
    "type": 8.0,
    "bt_tags": [],
    "pow": 0.0,
    "name": "Move"
  },
  "brine": {
    "id": "brine",
    "desc_tagids": [],
    "description": null,
    "targ": 0,
    "eff": [{ "eff": 33.0, "targ": 0.0, "pow": 9.0 }],
    "use": 0.0,
    "desc_tags": [],
    "type": 0.0,
    "bt_tags": [0],
    "pow": 55.0,
    "name": "Finisher"
  },
  "defense": {
    "id": "defense",
    "desc_tagids": [],
    "description": null,
    "targ": 4,
    "eff": [{ "eff": 27.0, "targ": 3.0, "pow": 1.0 }],
    "use": 2.0,
    "desc_tags": [],
    "type": 5.0,
    "bt_tags": [19, 9, 37],
    "pow": 0.0,
    "name": "Block"
  },
  "skillswap": {
    "id": "skillswap",
    "desc_tagids": [],
    "description": null,
    "targ": 5,
    "eff": [{ "eff": 63, "targ": 3, "pow": 1.0 }],
    "use": 0.0,
    "desc_tags": [],
    "type": 4.0,
    "bt_tags": [23, 9],
    "pow": 0.0,
    "name": "Trait Dance"
  },
  "powswitch": {
    "id": "powswitch",
    "desc_tagids": [],
    "description": null,
    "targ": 8,
    "eff": [
      { "eff": 30, "targ": 3.0, "pow": 1.0 },
      { "eff": 15.0, "targ": 3.0, "pow": 1.0 }
    ],
    "use": 0.0,
    "desc_tags": [],
    "type": 5.0,
    "bt_tags": [9, 18, 6],
    "pow": 0.0,
    "name": "Smack"
  },
  "mark": {
    "id": "mark",
    "desc_tagids": [],
    "description": null,
    "targ": 4,
    "eff": [{ "eff": 27.0, "targ": 3.0, "pow": 1.0 }],
    "use": 0.0,
    "desc_tags": [],
    "type": 4.0,
    "bt_tags": [23, 9, 37],
    "pow": 0.0,
    "name": "Mark"
  },
  "tailwind": {
    "id": "tailwind",
    "desc_tagids": [],
    "description": null,
    "targ": 3,
    "eff": [{ "eff": 7.0, "targ": 2.0, "pow": 1.0 }],
    "use": 0.0,
    "desc_tags": [],
    "type": 4.0,
    "bt_tags": [23, 9, 21],
    "pow": 0.0,
    "name": "Tailwind"
  },
  "volley": {
    "id": "volley",
    "desc_tagids": [],
    "description": null,
    "targ": 2,
    "eff": [],
    "use": 0.0,
    "desc_tags": [],
    "type": 3.0,
    "bt_tags": [22, 9],
    "pow": 0.0,
    "name": "Volley"
  },
  "3actions": {
    "id": "3actions",
    "desc_tagids": [],
    "description": null,
    "targ": 0,
    "eff": [{ "eff": 41.0, "targ": 0.0, "pow": 1.0 }],
    "use": 0.0,
    "desc_tags": [],
    "type": 0.0,
    "bt_tags": [0, 8, 30],
    "pow": 200.0,
    "name": "Ultimate Attack"
  },
  "hex": {
    "id": "hex",
    "desc_tagids": [],
    "description": null,
    "targ": 0,
    "eff": [{ "eff": 33.0, "targ": 0.0, "pow": 13 }],
    "use": 0.0,
    "desc_tags": [],
    "type": 2.0,
    "bt_tags": [2],
    "pow": 65.0,
    "name": "Nerve Strike"
  },
  "feint": {
    "id": "feint",
    "desc_tagids": [],
    "description": null,
    "targ": 4,
    "eff": [{ "eff": 16.0, "targ": 3.0, "pow": -1.0 }],
    "use": 0.0,
    "desc_tags": [],
    "type": 4.0,
    "bt_tags": [23, 9, 36, 6],
    "pow": 0.0,
    "name": "Feint"
  },
  "heartpass": {
    "id": "heartpass",
    "desc_tagids": [],
    "description": null,
    "targ": 2,
    "eff": [{ "eff": 1.0, "targ": 1.0, "pow": 1.0 }],
    "use": 0.0,
    "desc_tags": [],
    "type": 3.0,
    "bt_tags": [22, 9, 4],
    "pow": 0.0,
    "name": "Faith"
  },
  "bellydrum": {
    "id": "bellydrum",
    "desc_tagids": [],
    "description": null,
    "targ": 1,
    "eff": [
      { "eff": 1.0, "targ": 0.0, "pow": 3.0 },
      { "eff": 8.0, "targ": 0.0, "pow": -0.34000000000000002 }
    ],
    "use": 0.0,
    "desc_tags": [],
    "type": 4.0,
    "bt_tags": [23, 27, 30],
    "pow": 0.0,
    "name": "Blaze"
  },
  "inferno": {
    "id": "inferno",
    "desc_tagids": [],
    "description": null,
    "targ": 0,
    "eff": [
      { "eff": 36, "targ": 5, "pow": 1.0 },
      { "eff": 36, "targ": 2, "pow": 0.5 }
    ],
    "use": 0.0,
    "desc_tags": [],
    "type": 1.0,
    "bt_tags": [1, 38],
    "pow": 70.0,
    "name": "Explosion"
  },
  "dispel": {
    "id": "dispel",
    "desc_tagids": [],
    "description": null,
    "targ": 2,
    "eff": [{ "eff": 20, "targ": 1, "pow": 1.0 }],
    "use": 0.0,
    "desc_tags": [],
    "type": 4.0,
    "bt_tags": [23, 9],
    "pow": 0.0,
    "name": "Dispel"
  },
  "shaken": {
    "id": "shaken",
    "desc_tagids": [],
    "description": null,
    "targ": 4,
    "eff": [{ "eff": 13.0, "targ": 3.0, "pow": 2.0 }],
    "use": 0.0,
    "desc_tags": [],
    "type": 5.0,
    "bt_tags": [9, 37],
    "pow": 0.0,
    "name": "Stinky"
  },
  "xtra": {
    "id": "xtra",
    "desc_tagids": [],
    "description": null,
    "targ": 0.0,
    "eff": [],
    "use": 0.0,
    "desc_tags": [],
    "type": 6.0,
    "bt_tags": [],
    "pow": 0.0,
    "name": "Bonus"
  },
  "bounce": {
    "id": "bounce",
    "desc_tagids": [],
    "description": null,
    "targ": 0,
    "eff": [{ "eff": 17.0, "targ": 0.0, "pow": 0.0 }],
    "use": 0.0,
    "desc_tags": [],
    "type": 0.0,
    "bt_tags": [0],
    "pow": 35.0,
    "name": "Bump"
  },
  "enemylowered": {
    "id": "enemylowered",
    "desc_tagids": [],
    "description": null,
    "targ": 0,
    "eff": [{ "eff": 33, "targ": 0.0, "pow": 21 }],
    "use": 0.0,
    "desc_tags": [],
    "type": 2.0,
    "bt_tags": [2],
    "pow": 50.0,
    "name": "Pierce"
  },
  "mindup": {
    "id": "mindup",
    "desc_tagids": [],
    "description": null,
    "targ": 1,
    "eff": [{ "eff": 2.0, "targ": 0.0, "pow": 2.0 }],
    "use": 0.0,
    "desc_tags": [],
    "type": 5.0,
    "bt_tags": [27],
    "pow": 0.0,
    "name": "Assess"
  },
  "cheer": {
    "id": "cheer",
    "desc_tagids": [],
    "description": null,
    "targ": 2,
    "eff": [{ "eff": 15.0, "targ": 1.0, "pow": 1.0 }],
    "use": 0.0,
    "desc_tags": [],
    "type": 4.0,
    "bt_tags": [23, 9, 6],
    "pow": 0.0,
    "name": "Cheer"
  },
  "passattack": {
    "id": "passattack",
    "desc_tagids": [],
    "description": null,
    "targ": 0,
    "eff": [{ "eff": 33, "targ": 0.0, "pow": 19 }],
    "use": 0.0,
    "desc_tags": [],
    "type": 2.0,
    "bt_tags": [2],
    "pow": 50.0,
    "name": "Zigzag"
  },
  "bdefup": {
    "id": "bdefup",
    "desc_tagids": [],
    "description": null,
    "targ": 1,
    "eff": [{ "eff": 3.0, "targ": 0.0, "pow": 2.0 }],
    "use": 0.0,
    "desc_tags": [],
    "type": 5.0,
    "bt_tags": [28, 7],
    "pow": 0.0,
    "name": "Body Ready"
  },
  "myheartpass": {
    "id": "myheartpass",
    "desc_tagids": [],
    "description": null,
    "targ": 1,
    "eff": [{ "eff": 1.0, "targ": 0.0, "pow": 1.0 }],
    "use": 0.0,
    "desc_tags": [],
    "type": 3.0,
    "bt_tags": [22, 27],
    "pow": 0.0,
    "name": "Excited Pass"
  },
  "recover": {
    "id": "recover",
    "desc_tagids": [],
    "description": null,
    "targ": 1,
    "eff": [{ "eff": 8, "targ": 0.0, "pow": 0.29999999999999999 }],
    "use": 0.0,
    "desc_tags": [],
    "type": 4.0,
    "bt_tags": [23, 28],
    "pow": 0.0,
    "name": "Deep Breath"
  },
  "haze": {
    "id": "haze",
    "desc_tagids": [],
    "description": null,
    "targ": 1,
    "eff": [{ "eff": 34.0, "targ": 7.0, "pow": 1.0 }],
    "use": 0.0,
    "desc_tags": [],
    "type": 5.0,
    "bt_tags": [],
    "pow": 0.0,
    "name": "Patience"
  },
  "juggle": {
    "id": "juggle",
    "desc_tagids": [],
    "description": null,
    "targ": 1,
    "eff": [
      { "eff": 20.0, "targ": 0.0, "pow": 1.0 },
      { "eff": 0.0, "targ": 0.0, "pow": 1.0 }
    ],
    "use": 0.0,
    "desc_tags": [],
    "type": 3.0,
    "bt_tags": [22, 27],
    "pow": 0.0,
    "name": "Juggle"
  },
  "heartd": {
    "id": "heartd",
    "desc_tagids": [],
    "description": null,
    "targ": 0,
    "eff": [{ "eff": 4.0, "targ": 0.0, "pow": 1.0 }],
    "use": 0.0,
    "desc_tags": [],
    "type": 2.0,
    "bt_tags": [2, 28, 7],
    "pow": 60.0,
    "name": "Cold Calculation"
  },
  "rollshot": {
    "id": "rollshot",
    "desc_tagids": [],
    "description": null,
    "targ": 8,
    "eff": [{ "eff": 33.0, "targ": 0.0, "pow": 17.0 }],
    "use": 2.0,
    "desc_tags": [],
    "type": 2.0,
    "bt_tags": [2, 19, 9],
    "pow": 80.0,
    "name": "Roll Shot"
  },
  "protect": {
    "id": "protect",
    "desc_tagids": [],
    "description": null,
    "targ": 1,
    "eff": [
      { "eff": 53, "targ": 0.0, "pow": 0.0 },
      { "eff": 19, "targ": 0.0, "pow": 1.0 },
      { "eff": 12, "targ": 0.0, "pow": 2.0 }
    ],
    "use": 0.0,
    "desc_tags": [],
    "type": 5.0,
    "bt_tags": [32],
    "pow": 0.0,
    "name": "Shield"
  },
  "blockattack": {
    "id": "blockattack",
    "desc_tagids": [],
    "description": null,
    "targ": 1,
    "eff": [{ "eff": 17.0, "targ": 0.0, "pow": 0.0 }],
    "use": 2.0,
    "desc_tags": [],
    "type": 0.0,
    "bt_tags": [0, 19],
    "pow": 80.0,
    "name": "High Slam"
  },
  "wornout": {
    "id": "wornout",
    "desc_tagids": [],
    "description": null,
    "targ": 4,
    "eff": [
      { "eff": 29, "targ": 3, "pow": 4.0 },
      { "eff": 22, "targ": 0.0, "pow": 4.0 }
    ],
    "use": 0.0,
    "desc_tags": [],
    "type": 4.0,
    "bt_tags": [23, 9, 37, 30],
    "pow": 0.0,
    "name": "Hex"
  },
  "libero": {
    "id": "libero",
    "desc_tagids": [],
    "description": null,
    "targ": 4,
    "eff": [
      { "eff": 27.0, "targ": 3.0, "pow": 1.0 },
      { "eff": 8, "targ": 0.0, "pow": -0.10000000000000001 }
    ],
    "use": 0.0,
    "desc_tags": [],
    "type": 5.0,
    "bt_tags": [9, 37],
    "pow": 0.0,
    "name": "Hawkeye"
  },
  "defheal": {
    "id": "defheal",
    "desc_tagids": [],
    "description": null,
    "targ": 1,
    "eff": [{ "eff": 8.0, "targ": 0.0, "pow": 0.29999999999999999 }],
    "use": 0.0,
    "desc_tags": [],
    "type": 5.0,
    "bt_tags": [28],
    "pow": 0.0,
    "name": "Quick Breath"
  },
  "superfang": {
    "id": "superfang",
    "desc_tagids": [],
    "description": null,
    "targ": 0,
    "eff": [],
    "use": 0.0,
    "desc_tags": [],
    "type": 0.0,
    "bt_tags": [0],
    "pow": -0.5,
    "name": "Grinder"
  },
  "markattack": {
    "id": "markattack",
    "desc_tagids": [],
    "description": null,
    "targ": 0,
    "eff": [{ "eff": 27, "targ": 3, "pow": 1.0 }],
    "use": 0.0,
    "desc_tags": [],
    "type": 2.0,
    "bt_tags": [2, 37],
    "pow": 45.0,
    "name": "Tracker"
  },
  "telekinesis": {
    "id": "telekinesis",
    "desc_tagids": [],
    "description": null,
    "targ": 1,
    "eff": [
      { "eff": 20, "targ": 0.0, "pow": 1.0 },
      { "eff": 2.0, "targ": 0.0, "pow": 1.0 }
    ],
    "use": 0.0,
    "desc_tags": [],
    "type": 4.0,
    "bt_tags": [23, 27],
    "pow": 0.0,
    "name": "Telekinesis"
  },
  "careful": {
    "id": "careful",
    "desc_tagids": [],
    "description": null,
    "targ": 12,
    "eff": [],
    "use": 0.0,
    "desc_tags": [],
    "type": 1.0,
    "bt_tags": [1, 9],
    "pow": 40.0,
    "name": "Careful Shot"
  },
  "rhythm": {
    "id": "rhythm",
    "desc_tagids": [],
    "description": null,
    "targ": 0,
    "eff": [{ "eff": 44, "targ": 0, "pow": 6.0 }],
    "use": 0.0,
    "desc_tags": [],
    "type": 4.0,
    "bt_tags": [23, 13],
    "pow": 0.0,
    "name": "Drum"
  },
  "hdefup": {
    "id": "hdefup",
    "desc_tagids": [],
    "description": null,
    "targ": 1,
    "eff": [{ "eff": 4.0, "targ": 0.0, "pow": 2.0 }],
    "use": 0.0,
    "desc_tags": [],
    "type": 5.0,
    "bt_tags": [28, 7],
    "pow": 0.0,
    "name": "Heart Harden"
  },
  "trap": {
    "id": "trap",
    "desc_tagids": [],
    "description": null,
    "targ": 0,
    "eff": [{ "eff": 42, "targ": 3, "pow": 2.0 }],
    "use": 0.0,
    "desc_tags": [],
    "type": 4.0,
    "bt_tags": [23, 10],
    "pow": 0.0,
    "name": "Lay Trap"
  },
  "nice": {
    "id": "nice",
    "desc_tagids": [],
    "description": null,
    "targ": 0,
    "eff": [{ "eff": 18, "targ": 3, "pow": 0.0 }],
    "use": 0.0,
    "desc_tags": [],
    "type": 0.0,
    "bt_tags": [0],
    "pow": 95.0,
    "name": "Nice Shot"
  },
  "wornattack": {
    "id": "wornattack",
    "desc_tagids": [],
    "description": null,
    "targ": 0,
    "eff": [{ "eff": 40.0, "targ": 0.0, "pow": 1.0 }],
    "use": 0.0,
    "desc_tags": [],
    "type": 2.0,
    "bt_tags": [2, 8, 30],
    "pow": 125.0,
    "name": "Perfect Shot"
  },
  "basecover": {
    "id": "basecover",
    "desc_tagids": [],
    "description": null,
    "targ": 3,
    "eff": [{ "eff": 7.0, "targ": 2.0, "pow": 0.0 }],
    "use": 0.0,
    "desc_tags": [],
    "type": 5.0,
    "bt_tags": [9],
    "pow": 0.0,
    "name": "Fall Back"
  },
  "nightshade": {
    "id": "nightshade",
    "desc_tagids": [],
    "description": null,
    "targ": 8,
    "eff": [],
    "use": 0.0,
    "desc_tags": [],
    "type": 2.0,
    "bt_tags": [2, 9],
    "pow": -30.0,
    "name": "Precision"
  },
  "preblock": {
    "id": "preblock",
    "desc_tagids": [],
    "description": null,
    "targ": 1,
    "eff": [
      { "eff": 16.0, "targ": 0.0, "pow": 1.0 },
      { "eff": 6.0, "targ": 0.0, "pow": 1.0 }
    ],
    "use": 0.0,
    "desc_tags": [],
    "type": 4.0,
    "bt_tags": [23, 28, 7, 30],
    "pow": 0.0,
    "name": "Hunker"
  },
  "shieldbreaker": {
    "id": "shieldbreaker",
    "desc_tagids": [],
    "description": null,
    "targ": 0,
    "eff": [{ "eff": 33.0, "targ": 0.0, "pow": 14 }],
    "use": 0.0,
    "desc_tags": [],
    "type": 1.0,
    "bt_tags": [1],
    "pow": 65.0,
    "name": "Raw Fury"
  },
  "shakenhit": {
    "id": "shakenhit",
    "desc_tagids": [],
    "description": null,
    "targ": 4,
    "eff": [{ "eff": 13.0, "targ": 3.0, "pow": 1.0 }],
    "use": 0.0,
    "desc_tags": [],
    "type": 0.0,
    "bt_tags": [0, 9, 37],
    "pow": 0.0,
    "name": "Reach Shot"
  },
  "vigor": {
    "id": "vigor",
    "desc_tagids": [],
    "description": null,
    "targ": 0,
    "eff": [{ "eff": 33.0, "targ": 0.0, "pow": 0.0 }],
    "use": 2.0,
    "desc_tags": [],
    "type": 0.0,
    "bt_tags": [0, 8, 19],
    "pow": 135.0,
    "name": "Vigor Beam"
  },
  "starterbody": {
    "id": "starterbody",
    "desc_tagids": [],
    "description": null,
    "targ": 0,
    "eff": [],
    "use": 0.0,
    "desc_tags": [],
    "type": 0.0,
    "bt_tags": [0],
    "pow": 50.0,
    "name": "Basic Hit"
  },
  "dump": {
    "id": "dump",
    "desc_tagids": [],
    "description": null,
    "targ": 4,
    "eff": [],
    "use": 2.0,
    "desc_tags": [],
    "type": 2.0,
    "bt_tags": [2, 19, 9],
    "pow": 85.0,
    "name": "Dump"
  },
  "bench": {
    "id": "bench",
    "desc_tagids": [],
    "description": null,
    "targ": 8,
    "eff": [{ "eff": 30.0, "targ": 3.0, "pow": 1.0 }],
    "use": 0.0,
    "desc_tags": [],
    "type": 4.0,
    "bt_tags": [23, 9, 18],
    "pow": 0.0,
    "name": "Quick Tag"
  },
  "chance": {
    "id": "chance",
    "desc_tagids": [],
    "description": null,
    "targ": 0,
    "eff": [
      { "eff": 17.0, "targ": 0.0, "pow": 0.0 },
      { "eff": 18.0, "targ": 0.0, "pow": 0.0 }
    ],
    "use": 0.0,
    "desc_tags": [],
    "type": 0.0,
    "bt_tags": [0],
    "pow": -1.0,
    "name": "Free Ball"
  },
  "introduction": {
    "id": "introduction",
    "desc_tagids": [],
    "description": null,
    "targ": 8,
    "eff": [{ "eff": 19, "targ": 3, "pow": 1.0 }],
    "use": 0.0,
    "desc_tags": [],
    "type": 4.0,
    "bt_tags": [23, 9, 32],
    "pow": 0.0,
    "name": "Introduce"
  },
  "quickattack": {
    "id": "quickattack",
    "desc_tagids": [],
    "description": null,
    "targ": 2,
    "eff": [{ "eff": 0.0, "targ": 1.0, "pow": 1.0 }],
    "use": 0.0,
    "desc_tags": [],
    "type": 3.0,
    "bt_tags": [22, 9, 3],
    "pow": 0.0,
    "name": "Quick"
  },
  "starterside": {
    "id": "starterside",
    "desc_tagids": [],
    "description": null,
    "targ": 12,
    "eff": [{ "eff": 5, "targ": 3, "pow": -1.0 }],
    "use": 0.0,
    "desc_tags": [],
    "type": 2.0,
    "bt_tags": [2, 9, 36, 5],
    "pow": 35.0,
    "name": "Trickspin"
  },
  "rushattack": {
    "id": "rushattack",
    "desc_tagids": [],
    "description": null,
    "targ": 0,
    "eff": [
      { "eff": -7.0, "targ": 0.0, "pow": 1.0 },
      { "eff": 57, "targ": 0.0, "pow": 0.0 }
    ],
    "use": 1.0,
    "desc_tags": [],
    "type": 0.0,
    "bt_tags": [0, 8, 20],
    "pow": 100.0,
    "name": "Launch"
  },
  "lifedew": {
    "id": "lifedew",
    "desc_tagids": [],
    "description": null,
    "targ": 1,
    "eff": [{ "eff": 8, "targ": 2.0, "pow": 0.14999999999999999 }],
    "use": 0.0,
    "desc_tags": [],
    "type": 4.0,
    "bt_tags": [23, 16],
    "pow": 0.0,
    "name": "Calming Aura"
  },
  "backswitch": {
    "id": "backswitch",
    "desc_tagids": [],
    "description": null,
    "targ": 1,
    "eff": [{ "eff": 7.0, "targ": 2.0, "pow": 7.0 }],
    "use": 0.0,
    "desc_tags": [],
    "type": 5.0,
    "bt_tags": [],
    "pow": 0.0,
    "name": "Role Reverse"
  },
  "rocket": {
    "id": "rocket",
    "desc_tagids": [],
    "description": null,
    "targ": 0,
    "eff": [{ "eff": 33.0, "targ": 0.0, "pow": 16.0 }],
    "use": 0.0,
    "desc_tags": [],
    "type": 0.0,
    "bt_tags": [0],
    "pow": 70.0,
    "name": "Rocket"
  },
  "starterheart": {
    "id": "starterheart",
    "desc_tagids": [],
    "description": null,
    "targ": 0,
    "eff": [],
    "use": 0.0,
    "desc_tags": [],
    "type": 1.0,
    "bt_tags": [1],
    "pow": 45.0,
    "name": "Beginner Effort"
  },
  "pushattack": {
    "id": "pushattack",
    "desc_tagids": [],
    "description": null,
    "targ": 0,
    "eff": [{ "eff": 7, "targ": 3, "pow": 0.0 }],
    "use": 2.0,
    "desc_tags": [],
    "type": 0.0,
    "bt_tags": [0, 19],
    "pow": 75.0,
    "name": "Shove"
  },
  "chill": {
    "id": "chill",
    "desc_tagids": [],
    "description": null,
    "targ": 4,
    "eff": [{ "eff": 1, "targ": 3, "pow": -2.0 }],
    "use": 0.0,
    "desc_tags": [],
    "type": 4.0,
    "bt_tags": [23, 9, 36],
    "pow": 0.0,
    "name": "Chill Out"
  },
  "switch": {
    "id": "switch",
    "desc_tagids": [],
    "description": null,
    "targ": 1,
    "eff": [{ "eff": 11.0, "targ": 1.0, "pow": 1.0 }],
    "use": 0.0,
    "desc_tags": [],
    "type": 4.0,
    "bt_tags": [23],
    "pow": 0.0,
    "name": "Reposition"
  },
  "bomb": {
    "id": "bomb",
    "desc_tagids": [],
    "description": null,
    "targ": 0,
    "eff": [{ "eff": 36, "targ": 5, "pow": 0.5 }],
    "use": 0.0,
    "desc_tags": [],
    "type": 1.0,
    "bt_tags": [1, 38],
    "pow": 55.0,
    "name": "Bang"
  },
  "jump": {
    "id": "jump",
    "desc_tagids": [],
    "description": null,
    "targ": 0,
    "eff": [],
    "use": 2.0,
    "desc_tags": [],
    "type": 0.0,
    "bt_tags": [0, 8, 19],
    "pow": 100.0,
    "name": "Spike"
  },
  "eerie": {
    "id": "eerie",
    "desc_tagids": [],
    "description": null,
    "targ": 0,
    "eff": [
      { "eff": 7.0, "targ": 0.0, "pow": 1.0 },
      { "eff": 45, "targ": 7, "pow": 6.0 }
    ],
    "use": 0.0,
    "desc_tags": [],
    "type": 4.0,
    "bt_tags": [23, 40],
    "pow": 0.0,
    "name": "Dreadful Mist"
  },
  "flyback": {
    "id": "flyback",
    "desc_tagids": [],
    "description": null,
    "targ": 0,
    "eff": [
      { "eff": -7.0, "targ": 0.0, "pow": 0.0 },
      { "eff": 57, "targ": 0.0, "pow": 1.0 }
    ],
    "use": 2.0,
    "desc_tags": [],
    "type": 1.0,
    "bt_tags": [1, 8, 19],
    "pow": 130.0,
    "name": "Airblast"
  },
  "stun": {
    "id": "stun",
    "desc_tagids": [],
    "description": null,
    "targ": 0,
    "eff": [{ "eff": 6.0, "targ": 3.0, "pow": 1.0 }],
    "use": 0.0,
    "desc_tags": [],
    "type": 2.0,
    "bt_tags": [2, 29, 37],
    "pow": 40.0,
    "name": "Freezer"
  },
  "lock": {
    "id": "lock",
    "desc_tagids": [],
    "description": null,
    "targ": 4,
    "eff": [
      { "eff": 7.0, "targ": 0.0, "pow": 1.0 },
      { "eff": 6.0, "targ": 3.0, "pow": 1.0 }
    ],
    "use": 0.0,
    "desc_tags": [],
    "type": 5.0,
    "bt_tags": [9, 29, 37],
    "pow": 0.0,
    "name": "Staredown"
  },
  "healbell": {
    "id": "healbell",
    "desc_tagids": [],
    "description": null,
    "targ": 1,
    "eff": [{ "eff": 32, "targ": 6, "pow": 1.0 }],
    "use": 0.0,
    "desc_tags": [],
    "type": 4.0,
    "bt_tags": [23, 16],
    "pow": 0.0,
    "name": "Team Chant"
  },
  "batonpass": {
    "id": "batonpass",
    "desc_tagids": [],
    "description": null,
    "targ": 8,
    "eff": [
      { "eff": 31, "targ": 3.0, "pow": 1.0 },
      { "eff": 30, "targ": 3.0, "pow": 1.0 }
    ],
    "use": 0.0,
    "desc_tags": [],
    "type": 5.0,
    "bt_tags": [9, 17, 18],
    "pow": 0.0,
    "name": "High Five"
  },
  "mind": {
    "id": "mind",
    "desc_tagids": [],
    "description": null,
    "targ": 0,
    "eff": [{ "eff": 5.0, "targ": 0.0, "pow": 1.0 }],
    "use": 0.0,
    "desc_tags": [],
    "type": 2.0,
    "bt_tags": [2, 28, 7],
    "pow": 70.0,
    "name": "Prepared Attack"
  },
  "lockon": {
    "id": "lockon",
    "desc_tagids": [],
    "description": null,
    "targ": 4,
    "eff": [{ "eff": 14.0, "targ": 3.0, "pow": 1.0 }],
    "use": 0.0,
    "desc_tags": [],
    "type": 4.0,
    "bt_tags": [23, 9, 34],
    "pow": 0.0,
    "name": "Lock Target"
  },
  "stomp": {
    "id": "stomp",
    "desc_tagids": [],
    "description": null,
    "targ": 0,
    "eff": [
      { "eff": 12, "targ": 0, "pow": 1.0 },
      { "eff": 64, "targ": 0, "pow": 2 },
      { "eff": 0, "targ": 0, "pow": 1.0 }
    ],
    "use": 0.0,
    "desc_tags": [],
    "type": 0.0,
    "bt_tags": [0, 27],
    "pow": 85.0,
    "name": "Stomp"
  },
  "healhit": {
    "id": "healhit",
    "desc_tagids": [],
    "description": null,
    "targ": 0,
    "eff": [{ "eff": 8.0, "targ": 0.0, "pow": 0.20000000000000001 }],
    "use": 0.0,
    "desc_tags": [],
    "type": 0.0,
    "bt_tags": [0],
    "pow": 50.0,
    "name": "Relaxed Hit"
  }
}
